ggscrap/__init__.py
ggscrap/scrap_MP.py
ggscrap/scrap_base.py
ggscrap-0.1.3.dist-info/METADATA
ggscrap-0.1.3.dist-info/WHEEL
ggscrap-0.1.3.dist-info/top_level.txt
ggscrap-0.1.3.dist-info/RECORD
